sequentPSS/__init__.py
sequentPSS/sequentPSS.py
sequentPSS/sampleData/O1.txt
sequentPSS/sampleData/O2.txt
sequentPSS/sampleData/O3.txt
sequentPSS/sampleData/concatenated_df.csv
sequentPSS-0.1.3.dist-info/METADATA
sequentPSS-0.1.3.dist-info/WHEEL
sequentPSS-0.1.3.dist-info/top_level.txt
sequentPSS-0.1.3.dist-info/RECORD
